LICENSE
MANIFEST.in
setup.py
symposion/__init__.py
symposion/conf.py
symposion/forms.py
symposion/markdown_parser.py
symposion/models.py
symposion/views.py
symposion.egg-info/PKG-INFO
symposion.egg-info/SOURCES.txt
symposion.egg-info/dependency_links.txt
symposion.egg-info/top_level.txt
symposion/boxes/__init__.py
symposion/boxes/admin.py
symposion/boxes/authorization.py
symposion/boxes/forms.py
symposion/boxes/models.py
symposion/boxes/urls.py
symposion/boxes/utils.py
symposion/boxes/views.py
symposion/boxes/templatetags/__init__.py
symposion/boxes/templatetags/boxes_tags.py
symposion/cms/__init__.py
symposion/cms/admin.py
symposion/cms/forms.py
symposion/cms/managers.py
symposion/cms/models.py
symposion/cms/urls.py
symposion/cms/views.py
symposion/conference/__init__.py
symposion/conference/admin.py
symposion/conference/models.py
symposion/conference/urls.py
symposion/conference/views.py
symposion/proposals/__init__.py
symposion/proposals/actions.py
symposion/proposals/admin.py
symposion/proposals/forms.py
symposion/proposals/managers.py
symposion/proposals/models.py
symposion/proposals/urls.py
symposion/proposals/views.py
symposion/proposals/templatetags/__init__.py
symposion/proposals/templatetags/proposal_tags.py
symposion/reviews/__init__.py
symposion/reviews/admin.py
symposion/reviews/context_processors.py
symposion/reviews/fixture_gen.py
symposion/reviews/forms.py
symposion/reviews/models.py
symposion/reviews/tests.py
symposion/reviews/urls.py
symposion/reviews/utils.py
symposion/reviews/views.py
symposion/reviews/management/__init__.py
symposion/reviews/management/commands/__init__.py
symposion/reviews/management/commands/calculate_results.py
symposion/reviews/management/commands/create_review_permissions.py
symposion/reviews/management/commands/promoteproposals.py
symposion/reviews/templatetags/__init__.py
symposion/reviews/templatetags/review_tags.py
symposion/schedule/__init__.py
symposion/schedule/admin.py
symposion/schedule/forms.py
symposion/schedule/helpers.py
symposion/schedule/models.py
symposion/schedule/timetable.py
symposion/schedule/urls.py
symposion/schedule/views.py
