Metadata-Version: 1.1
Name: symposion
Version: 1.0b2.dev2
Summary: A collection of Django apps for conference websites.
Home-page: http://pinax.github.com/symposion/
Author: James Tauber
Author-email: jtauber@jtauber.com
License: UNKNOWN
Platform: UNKNOWN
Classifier: Development Status :: 4 - Beta
Classifier: Programming Language :: Python
Classifier: Framework :: Django
Classifier: Intended Audience :: Developers
Classifier: Natural Language :: English
Classifier: License :: OSI Approved :: MIT License
